CHANGES.txt
MANIFEST.in
README.txt
setup.py
slapprepare/__init__.py
slapprepare/autoupdate.py
slapprepare/slapprepare.py
slapprepare/slapupdate.py
slapprepare.egg-info/PKG-INFO
slapprepare.egg-info/SOURCES.txt
slapprepare.egg-info/dependency_links.txt
slapprepare.egg-info/entry_points.txt
slapprepare.egg-info/not-zip-safe
slapprepare.egg-info/requires.txt
slapprepare.egg-info/top_level.txt
slapprepare/script/run_slapformat
slapprepare/script/slapos
slapprepare/script/slapos.service
slapprepare/script/slapos_firstboot
slapprepare/template/clientipv4.conf.in
slapprepare/template/hosts.in
slapprepare/template/ifcfg-br0.in
slapprepare/template/limits.conf.in
slapprepare/template/sshd_config.in