Metadata-Version: 1.0
Name: slapprepare
Version: 1.0a6
Summary: SlapOS Setup kit for dedicated SuSE machines.
Home-page: http://www.slapos.org
Author: VIFIB
Author-email: UNKNOWN
License: GPLv3
Keywords: slapos Setup Kit
Platform: UNKNOWN
Classifier: Programming Language :: Python
